site_discovery/__init__.py
site_discovery/get_sites.py
site_discovery/server_info.py
site_discovery/site_info.py
site_discovery-0.5.5.dist-info/DESCRIPTION.rst
site_discovery-0.5.5.dist-info/METADATA
site_discovery-0.5.5.dist-info/RECORD
site_discovery-0.5.5.dist-info/WHEEL
site_discovery-0.5.5.dist-info/entry_points.txt
site_discovery-0.5.5.dist-info/metadata.json
site_discovery-0.5.5.dist-info/pbr.json
site_discovery-0.5.5.dist-info/top_level.txt
