Metadata-Version: 2.0
Name: site-discovery
Version: 0.5.5
Summary: Site discovery tools for virtual hostings
Home-page: https://github.com/viasite/site-discovery
Author: Viasite
Author-email: popstas@gmail.com
License: MIT
Download-URL: https://github.com/viasite/site-discovery/archive/master.zip
Platform: UNKNOWN
Classifier: Development Status :: 2 - Pre-Alpha
Classifier: Environment :: Console
Classifier: Intended Audience :: Developers
Classifier: Intended Audience :: System Administrators
Classifier: License :: OSI Approved :: MIT License
Classifier: Operating System :: POSIX :: Linux
Classifier: Programming Language :: Python :: 3.5
Classifier: Topic :: System :: Monitoring
Requires-Dist: influxdb (>=4.0.0)
Requires-Dist: openpyxl (>=2.4.0)
Requires-Dist: pbr (==3.0.1)
Requires-Dist: termcolor (>=1.1.0)
Requires-Dist: PyYAML
Requires-Dist: sh
